flask_app/__init__.py
flask_app/routes.py
seq_to_first_iso/__init__.py
seq_to_first_iso/seq_to_first_iso.py
seq_to_first_iso-1.1.0.dist-info/LICENSE.txt
seq_to_first_iso-1.1.0.dist-info/METADATA
seq_to_first_iso-1.1.0.dist-info/WHEEL
seq_to_first_iso-1.1.0.dist-info/entry_points.txt
seq_to_first_iso-1.1.0.dist-info/top_level.txt
seq_to_first_iso-1.1.0.dist-info/RECORD
