Metadata-Version: 2.1
Name: seq-to-first-iso
Version: 1.1.0
Summary: Compute first two isotopologues intensity from peptide sequence.
Home-page: https://github.com/pierrepo/seq-to-first-iso
Author: Lilian Yang-crosson, Pierre Poulain
Author-email: pierre.poulain@cupnet.net
License: BSD 3-Clause License
Keywords: proteomics,spectrometry,isotopologues
Platform: UNKNOWN
Classifier: Development Status :: 4 - Beta
Classifier: Intended Audience :: Science/Research
Classifier: Topic :: Scientific/Engineering
Classifier: Topic :: Scientific/Engineering :: Bio-Informatics
Classifier: Topic :: Scientific/Engineering :: Chemistry
Classifier: Natural Language :: English
Classifier: Programming Language :: Python
Classifier: Programming Language :: Python :: 3
Classifier: Programming Language :: Python :: 3.6
Classifier: Programming Language :: Python :: 3.7
Classifier: Programming Language :: Python :: 3.8
Requires-Python: >=3.6
Requires-Dist: pandas
Requires-Dist: pyteomics[unimod]
